Workbook

Sheet Annual Summary
A1: Six Peak Capital - Annual Summary
B2: FY 2026 | C2: FY 2027 | D2: FY 2028 | E2: FY 2029 | F2: FY 2030 | G2: FY 2031 | H2: FY 2032 | I2: FY 2033
A3: Construction Billing | B3: =Model!C7+Model!D7+Model!E7+Model!F7+Model!G7+Model!H7+Model!I7+Model!J7+Model!K7 -> 52369472 | C3: =Model!L7+Model!M7+Model!N7+Model!O7+Model!P7+Model!Q7+Model!R7+Model!S7+Model!T7+Model!U7+Model!V7+Model!W7 -> 87410003 | D3: =Model!X7+Model!Y7+Model!Z7+Model!AA7+Model!AB7+Model!AC7+Model!AD7+Model!AE7+Model!AF7+Model!AG7+Model!AH7+Model!AI7 -> 53453481 | E3: =Model!AJ7+Model!AK7+Model!AL7+Model!AM7+Model!AN7+Model!AO7+Model!AP7+Model!AQ7+Model!AR7+Model!AS7+Model!AT7+Model!AU7 -> 62244171 | F3: =Model!AV7+Model!AW7+Model!AX7+Model!AY7+Model!AZ7+Model!BA7+Model!BB7+Model!BC7+Model!BD7+Model!BE7+Model!BF7+Model!BG7 -> 61258750 | G3: =Model!BH7+Model!BI7+Model!BJ7+Model!BK7+Model!BL7+Model!BM7+Model!BN7+Model!BO7+Model!BP7+Model!BQ7+Model!BR7+Model!BS7 -> 48397755 | H3: =Model!BT7+Model!BU7+Model!BV7+Model!BW7+Model!BX7+Model!BY7+Model!BZ7+Model!CA7+Model!CB7+Model!CC7+Model!CD7+Model!CE7 -> 56955885 | I3: =Model!CF7+Model!CG7+Model!CH7 -> 10628505
A4: GC Revenue
A5: Project Supervision | B5: =Model!C8+Model!D8+Model!E8+Model!F8+Model!G8+Model!H8+Model!I8+Model!J8+Model!K8 -> 2163853.8 | C5: =Model!L8+Model!M8+Model!N8+Model!O8+Model!P8+Model!Q8+Model!R8+Model!S8+Model!T8+Model!U8+Model!V8+Model!W8 -> 3706998.8 | D5: =Model!X8+Model!Y8+Model!Z8+Model!AA8+Model!AB8+Model!AC8+Model!AD8+Model!AE8+Model!AF8+Model!AG8+Model!AH8+Model!AI8 -> 3236307.6 | E5: =Model!AJ8+Model!AK8+Model!AL8+Model!AM8+Model!AN8+Model!AO8+Model!AP8+Model!AQ8+Model!AR8+Model!AS8+Model!AT8+Model!AU8 -> 2930680.3 | F5: =Model!AV8+Model!AW8+Model!AX8+Model!AY8+Model!AZ8+Model!BA8+Model!BB8+Model!BC8+Model!BD8+Model!BE8+Model!BF8+Model!BG8 -> 3139915.3 | G5: =Model!BH8+Model!BI8+Model!BJ8+Model!BK8+Model!BL8+Model!BM8+Model!BN8+Model!BO8+Model!BP8+Model!BQ8+Model!BR8+Model!BS8 -> 2374188.3 | H5: =Model!BT8+Model!BU8+Model!BV8+Model!BW8+Model!BX8+Model!BY8+Model!BZ8+Model!CA8+Model!CB8+Model!CC8+Model!CD8+Model!CE8 -> 2644480.5 | I5: =Model!CF8+Model!CG8+Model!CH8 -> 460227.27
A6: GC-CM Fee | B6: =Model!C9+Model!D9+Model!E9+Model!F9+Model!G9+Model!H9+Model!I9+Model!J9+Model!K9 -> 2440290.7 | C6: =Model!L9+Model!M9+Model!N9+Model!O9+Model!P9+Model!Q9+Model!R9+Model!S9+Model!T9+Model!U9+Model!V9+Model!W9 -> 4166268.3 | D6: =Model!X9+Model!Y9+Model!Z9+Model!AA9+Model!AB9+Model!AC9+Model!AD9+Model!AE9+Model!AF9+Model!AG9+Model!AH9+Model!AI9 -> 2662679.6 | E6: =Model!AJ9+Model!AK9+Model!AL9+Model!AM9+Model!AN9+Model!AO9+Model!AP9+Model!AQ9+Model!AR9+Model!AS9+Model!AT9+Model!AU9 -> 3028614.2 | F6: =Model!AV9+Model!AW9+Model!AX9+Model!AY9+Model!AZ9+Model!BA9+Model!BB9+Model!BC9+Model!BD9+Model!BE9+Model!BF9+Model!BG9 -> 3051796 | G6: =Model!BH9+Model!BI9+Model!BJ9+Model!BK9+Model!BL9+Model!BM9+Model!BN9+Model!BO9+Model!BP9+Model!BQ9+Model!BR9+Model!BS9 -> 2356065 | H6: =Model!BT9+Model!BU9+Model!BV9+Model!BW9+Model!BX9+Model!BY9+Model!BZ9+Model!CA9+Model!CB9+Model!CC9+Model!CD9+Model!CE9 -> 2752017.4 | I6: =Model!CF9+Model!CG9+Model!CH9 -> 491740.9
A7: Project Administration | B7: =Model!C10+Model!D10+Model!E10+Model!F10+Model!G10+Model!H10+Model!I10+Model!J10+Model!K10 -> 602077.86 | C7: =Model!L10+Model!M10+Model!N10+Model!O10+Model!P10+Model!Q10+Model!R10+Model!S10+Model!T10+Model!U10+Model!V10+Model!W10 -> 1135155.7 | D7: =Model!X10+Model!Y10+Model!Z10+Model!AA10+Model!AB10+Model!AC10+Model!AD10+Model!AE10+Model!AF10+Model!AG10+Model!AH10+Model!AI10 -> 1078769.2 | E7: =Model!AJ10+Model!AK10+Model!AL10+Model!AM10+Model!AN10+Model!AO10+Model!AP10+Model!AQ10+Model!AR10+Model!AS10+Model!AT10+Model!AU10 -> 976893.44 | F7: =Model!AV10+Model!AW10+Model!AX10+Model!AY10+Model!AZ10+Model!BA10+Model!BB10+Model!BC10+Model!BD10+Model!BE10+Model!BF10+Model!BG10 -> 1046638.4 | G7: =Model!BH10+Model!BI10+Model!BJ10+Model!BK10+Model!BL10+Model!BM10+Model!BN10+Model!BO10+Model!BP10+Model!BQ10+Model!BR10+Model!BS10 -> 791396.1 | H7: =Model!BT10+Model!BU10+Model!BV10+Model!BW10+Model!BX10+Model!BY10+Model!BZ10+Model!CA10+Model!CB10+Model!CC10+Model!CD10+Model!CE10 -> 881493.51 | I7: =Model!CF10+Model!CG10+Model!CH10 -> 153409.09
A8: Bonding Revenue | B8: =Model!C11+Model!D11+Model!E11+Model!F11+Model!G11+Model!H11+Model!I11+Model!J11+Model!K11 -> 1405537.6 | C8: =Model!L11+Model!M11+Model!N11+Model!O11+Model!P11+Model!Q11+Model!R11+Model!S11+Model!T11+Model!U11+Model!V11+Model!W11 -> 679001.55 | D8: =Model!X11+Model!Y11+Model!Z11+Model!AA11+Model!AB11+Model!AC11+Model!AD11+Model!AE11+Model!AF11+Model!AG11+Model!AH11+Model!AI11 -> 620319.48 | E8: =Model!AJ11+Model!AK11+Model!AL11+Model!AM11+Model!AN11+Model!AO11+Model!AP11+Model!AQ11+Model!AR11+Model!AS11+Model!AT11+Model!AU11 -> 0 | F8: =Model!AV11+Model!AW11+Model!AX11+Model!AY11+Model!AZ11+Model!BA11+Model!BB11+Model!BC11+Model!BD11+Model!BE11+Model!BF11+Model!BG11 -> 0 | G8: =Model!BH11+Model!BI11+Model!BJ11+Model!BK11+Model!BL11+Model!BM11+Model!BN11+Model!BO11+Model!BP11+Model!BQ11+Model!BR11+Model!BS11 -> 0 | H8: =Model!BT11+Model!BU11+Model!BV11+Model!BW11+Model!BX11+Model!BY11+Model!BZ11+Model!CA11+Model!CB11+Model!CC11+Model!CD11+Model!CE11 -> 0 | I8: =Model!CF11+Model!CG11+Model!CH11 -> 0
A9: Total GC Revenue | B9: =Model!C12+Model!D12+Model!E12+Model!F12+Model!G12+Model!H12+Model!I12+Model!J12+Model!K12 -> 6611760 | C9: =Model!L12+Model!M12+Model!N12+Model!O12+Model!P12+Model!Q12+Model!R12+Model!S12+Model!T12+Model!U12+Model!V12+Model!W12 -> 9687424.3 | D9: =Model!X12+Model!Y12+Model!Z12+Model!AA12+Model!AB12+Model!AC12+Model!AD12+Model!AE12+Model!AF12+Model!AG12+Model!AH12+Model!AI12 -> 7598075.8 | E9: =Model!AJ12+Model!AK12+Model!AL12+Model!AM12+Model!AN12+Model!AO12+Model!AP12+Model!AQ12+Model!AR12+Model!AS12+Model!AT12+Model!AU12 -> 6936188 | F9: =Model!AV12+Model!AW12+Model!AX12+Model!AY12+Model!AZ12+Model!BA12+Model!BB12+Model!BC12+Model!BD12+Model!BE12+Model!BF12+Model!BG12 -> 7238349.8 | G9: =Model!BH12+Model!BI12+Model!BJ12+Model!BK12+Model!BL12+Model!BM12+Model!BN12+Model!BO12+Model!BP12+Model!BQ12+Model!BR12+Model!BS12 -> 5521649.4 | H9: =Model!BT12+Model!BU12+Model!BV12+Model!BW12+Model!BX12+Model!BY12+Model!BZ12+Model!CA12+Model!CB12+Model!CC12+Model!CD12+Model!CE12 -> 6277991.4 | I9: =Model!CF12+Model!CG12+Model!CH12 -> 1105377.3
A11: GC Costs
A12: Bonding Costs | B12: =Model!C15+Model!D15+Model!E15+Model!F15+Model!G15+Model!H15+Model!I15+Model!J15+Model!K15 -> -693398.56 | C12: =Model!L15+Model!M15+Model!N15+Model!O15+Model!P15+Model!Q15+Model!R15+Model!S15+Model!T15+Model!U15+Model!V15+Model!W15 -> -1471170 | D12: =Model!X15+Model!Y15+Model!Z15+Model!AA15+Model!AB15+Model!AC15+Model!AD15+Model!AE15+Model!AF15+Model!AG15+Model!AH15+Model!AI15 -> -1344025.5 | E12: =Model!AJ15+Model!AK15+Model!AL15+Model!AM15+Model!AN15+Model!AO15+Model!AP15+Model!AQ15+Model!AR15+Model!AS15+Model!AT15+Model!AU15 -> 0 | F12: =Model!AV15+Model!AW15+Model!AX15+Model!AY15+Model!AZ15+Model!BA15+Model!BB15+Model!BC15+Model!BD15+Model!BE15+Model!BF15+Model!BG15 -> 0 | G12: =Model!BH15+Model!BI15+Model!BJ15+Model!BK15+Model!BL15+Model!BM15+Model!BN15+Model!BO15+Model!BP15+Model!BQ15+Model!BR15+Model!BS15 -> 0 | H12: =Model!BT15+Model!BU15+Model!BV15+Model!BW15+Model!BX15+Model!BY15+Model!BZ15+Model!CA15+Model!CB15+Model!CC15+Model!CD15+Model!CE15 -> 0 | I12: =Model!CF15+Model!CG15+Model!CH15 -> 0
A13: GC Personnel | B13: =Model!C16+Model!C17+Model!D16+Model!D17+Model!E16+Model!E17+Model!F16+Model!F17+Model!G16+Model!G17+Model!H16+Model!H17+Model!I16+Model!I17+Model!J16+Model!J17+Model!K16+Model!K17 -> -2218919 | C13: =Model!L16+Model!L17+Model!M16+Model!M17+Model!N16+Model!N17+Model!O16+Model!O17+Model!P16+Model!P17+Model!Q16+Model!Q17+Model!R16+Model!R17+Model!S16+Model!S17+Model!T16+Model!T17+Model!U16+Model!U17+Model!V16+Model!V17+Model!W16+Model!W17 -> -3086892 | D13: =Model!X16+Model!X17+Model!Y16+Model!Y17+Model!Z16+Model!Z17+Model!AA16+Model!AA17+Model!AB16+Model!AB17+Model!AC16+Model!AC17+Model!AD16+Model!AD17+Model!AE16+Model!AE17+Model!AF16+Model!AF17+Model!AG16+Model!AG17+Model!AH16+Model!AH17+Model!AI16+Model!AI17 -> -3086892 | E13: =Model!AJ16+Model!AJ17+Model!AK16+Model!AK17+Model!AL16+Model!AL17+Model!AM16+Model!AM17+Model!AN16+Model!AN17+Model!AO16+Model!AO17+Model!AP16+Model!AP17+Model!AQ16+Model!AQ17+Model!AR16+Model!AR17+Model!AS16+Model!AS17+Model!AT16+Model!AT17+Model!AU16+Model!AU17 -> -3086892 | F13: =Model!AV16+Model!AV17+Model!AW16+Model!AW17+Model!AX16+Model!AX17+Model!AY16+Model!AY17+Model!AZ16+Model!AZ17+Model!BA16+Model!BA17+Model!BB16+Model!BB17+Model!BC16+Model!BC17+Model!BD16+Model!BD17+Model!BE16+Model!BE17+Model!BF16+Model!BF17+Model!BG16+Model!BG17 -> -3086892 | G13: =Model!BH16+Model!BH17+Model!BI16+Model!BI17+Model!BJ16+Model!BJ17+Model!BK16+Model!BK17+Model!BL16+Model!BL17+Model!BM16+Model!BM17+Model!BN16+Model!BN17+Model!BO16+Model!BO17+Model!BP16+Model!BP17+Model!BQ16+Model!BQ17+Model!BR16+Model!BR17+Model!BS16+Model!BS17 -> -3086892 | H13: =Model!BT16+Model!BT17+Model!BU16+Model!BU17+Model!BV16+Model!BV17+Model!BW16+Model!BW17+Model!BX16+Model!BX17+Model!BY16+Model!BY17+Model!BZ16+Model!BZ17+Model!CA16+Model!CA17+Model!CB16+Model!CB17+Model!CC16+Model!CC17+Model!CD16+Model!CD17+Model!CE16+Model!CE17 -> -3086892 | I13: =Model!CF16+Model!CF17+Model!CG16+Model!CG17+Model!CH16+Model!CH17 -> -771723
A14: SP Allocated to LV | B14: =Model!C18+Model!D18+Model!E18+Model!F18+Model!G18+Model!H18+Model!I18+Model!J18+Model!K18 -> -555750 | C14: =Model!L18+Model!M18+Model!N18+Model!O18+Model!P18+Model!Q18+Model!R18+Model!S18+Model!T18+Model!U18+Model!V18+Model!W18 -> -741000 | D14: =Model!X18+Model!Y18+Model!Z18+Model!AA18+Model!AB18+Model!AC18+Model!AD18+Model!AE18+Model!AF18+Model!AG18+Model!AH18+Model!AI18 -> -741000 | E14: =Model!AJ18+Model!AK18+Model!AL18+Model!AM18+Model!AN18+Model!AO18+Model!AP18+Model!AQ18+Model!AR18+Model!AS18+Model!AT18+Model!AU18 -> -741000 | F14: =Model!AV18+Model!AW18+Model!AX18+Model!AY18+Model!AZ18+Model!BA18+Model!BB18+Model!BC18+Model!BD18+Model!BE18+Model!BF18+Model!BG18 -> -741000 | G14: =Model!BH18+Model!BI18+Model!BJ18+Model!BK18+Model!BL18+Model!BM18+Model!BN18+Model!BO18+Model!BP18+Model!BQ18+Model!BR18+Model!BS18 -> -741000 | H14: =Model!BT18+Model!BU18+Model!BV18+Model!BW18+Model!BX18+Model!BY18+Model!BZ18+Model!CA18+Model!CB18+Model!CC18+Model!CD18+Model!CE18 -> -741000 | I14: =Model!CF18+Model!CG18+Model!CH18 -> -185250
A15: Total GC Costs | B15: =Model!C39+Model!D39+Model!E39+Model!F39+Model!G39+Model!H39+Model!I39+Model!J39+Model!K39 -> -4166758.1 | C15: =Model!L39+Model!M39+Model!N39+Model!O39+Model!P39+Model!Q39+Model!R39+Model!S39+Model!T39+Model!U39+Model!V39+Model!W39 -> -6347671.4 | D15: =Model!X39+Model!Y39+Model!Z39+Model!AA39+Model!AB39+Model!AC39+Model!AD39+Model!AE39+Model!AF39+Model!AG39+Model!AH39+Model!AI39 -> -6306439.9 | E15: =Model!AJ39+Model!AK39+Model!AL39+Model!AM39+Model!AN39+Model!AO39+Model!AP39+Model!AQ39+Model!AR39+Model!AS39+Model!AT39+Model!AU39 -> -4940485.5 | F15: =Model!AV39+Model!AW39+Model!AX39+Model!AY39+Model!AZ39+Model!BA39+Model!BB39+Model!BC39+Model!BD39+Model!BE39+Model!BF39+Model!BG39 -> -4960718.2 | G15: =Model!BH39+Model!BI39+Model!BJ39+Model!BK39+Model!BL39+Model!BM39+Model!BN39+Model!BO39+Model!BP39+Model!BQ39+Model!BR39+Model!BS39 -> -4969115.4 | H15: =Model!BT39+Model!BU39+Model!BV39+Model!BW39+Model!BX39+Model!BY39+Model!BZ39+Model!CA39+Model!CB39+Model!CC39+Model!CD39+Model!CE39 -> -4881680.7 | I15: =Model!CF39+Model!CG39+Model!CH39 -> -1207458.1
A16: GC Net Income | B16: =Model!C41+Model!D41+Model!E41+Model!F41+Model!G41+Model!H41+Model!I41+Model!J41+Model!K41 -> 2445001.9 | C16: =Model!L41+Model!M41+Model!N41+Model!O41+Model!P41+Model!Q41+Model!R41+Model!S41+Model!T41+Model!U41+Model!V41+Model!W41 -> 3339752.9 | D16: =Model!X41+Model!Y41+Model!Z41+Model!AA41+Model!AB41+Model!AC41+Model!AD41+Model!AE41+Model!AF41+Model!AG41+Model!AH41+Model!AI41 -> 1291636 | E16: =Model!AJ41+Model!AK41+Model!AL41+Model!AM41+Model!AN41+Model!AO41+Model!AP41+Model!AQ41+Model!AR41+Model!AS41+Model!AT41+Model!AU41 -> 1995702.4 | F16: =Model!AV41+Model!AW41+Model!AX41+Model!AY41+Model!AZ41+Model!BA41+Model!BB41+Model!BC41+Model!BD41+Model!BE41+Model!BF41+Model!BG41 -> 2277631.6 | G16: =Model!BH41+Model!BI41+Model!BJ41+Model!BK41+Model!BL41+Model!BM41+Model!BN41+Model!BO41+Model!BP41+Model!BQ41+Model!BR41+Model!BS41 -> 552533.94 | H16: =Model!BT41+Model!BU41+Model!BV41+Model!BW41+Model!BX41+Model!BY41+Model!BZ41+Model!CA41+Model!CB41+Model!CC41+Model!CD41+Model!CE41 -> 1396310.8 | I16: =Model!CF41+Model!CG41+Model!CH41 -> -102080.87
A17: GC Profit Margin % | B17: =IF((Model!C12+Model!D12+Model!E12+Model!F12+Model!G12+Model!H12+Model!I12+Model!J12+Model!K12)<>0,(Model!C41+Model!D41+Model!E41+Model!F41+Model!G41+Model!H41+Model!I41+Model!J41+Model!K41)/(Model!C12+Model!D12+Model!E12+Model!F12+Model!G12+Model!H12+Model!I12+Model!J12+Model!K12),0) -> 0.36979593 | C17: =IF((Model!L12+Model!M12+Model!N12+Model!O12+Model!P12+Model!Q12+Model!R12+Model!S12+Model!T12+Model!U12+Model!V12+Model!W12)<>0,(Model!L41+Model!M41+Model!N41+Model!O41+Model!P41+Model!Q41+Model!R41+Model!S41+Model!T41+Model!U41+Model!V41+Model!W41)/(Model!L12+Model!M12+Model!N12+Model!O12+Model!P12+Model!Q12+Model!R12+Model!S12+Model!T12+Model!U12+Model!V12+Model!W12),0) -> 0.34475138 | D17: =IF((Model!X12+Model!Y12+Model!Z12+Model!AA12+Model!AB12+Model!AC12+Model!AD12+Model!AE12+Model!AF12+Model!AG12+Model!AH12+Model!AI12)<>0,(Model!X41+Model!Y41+Model!Z41+Model!AA41+Model!AB41+Model!AC41+Model!AD41+Model!AE41+Model!AF41+Model!AG41+Model!AH41+Model!AI41)/(Model!X12+Model!Y12+Model!Z12+Model!AA12+Model!AB12+Model!AC12+Model!AD12+Model!AE12+Model!AF12+Model!AG12+Model!AH12+Model!AI12),0) -> 0.16999514 | E17: =IF((Model!AJ12+Model!AK12+Model!AL12+Model!AM12+Model!AN12+Model!AO12+Model!AP12+Model!AQ12+Model!AR12+Model!AS12+Model!AT12+Model!AU12)<>0,(Model!AJ41+Model!AK41+Model!AL41+Model!AM41+Model!AN41+Model!AO41+Model!AP41+Model!AQ41+Model!AR41+Model!AS41+Model!AT41+Model!AU41)/(Model!AJ12+Model!AK12+Model!AL12+Model!AM12+Model!AN12+Model!AO12+Model!AP12+Model!AQ12+Model!AR12+Model!AS12+Model!AT12+Model!AU12),0) -> 0.28772324 | F17: =IF((Model!AV12+Model!AW12+Model!AX12+Model!AY12+Model!AZ12+Model!BA12+Model!BB12+Model!BC12+Model!BD12+Model!BE12+Model!BF12+Model!BG12)<>0,(Model!AV41+Model!AW41+Model!AX41+Model!AY41+Model!AZ41+Model!BA41+Model!BB41+Model!BC41+Model!BD41+Model!BE41+Model!BF41+Model!BG41)/(Model!AV12+Model!AW12+Model!AX12+Model!AY12+Model!AZ12+Model!BA12+Model!BB12+Model!BC12+Model!BD12+Model!BE12+Model!BF12+Model!BG12),0) -> 0.31466172 | G17: =IF((Model!BH12+Model!BI12+Model!BJ12+Model!BK12+Model!BL12+Model!BM12+Model!BN12+Model!BO12+Model!BP12+Model!BQ12+Model!BR12+Model!BS12)<>0,(Model!BH41+Model!BI41+Model!BJ41+Model!BK41+Model!BL41+Model!BM41+Model!BN41+Model!BO41+Model!BP41+Model!BQ41+Model!BR41+Model!BS41)/(Model!BH12+Model!BI12+Model!BJ12+Model!BK12+Model!BL12+Model!BM12+Model!BN12+Model!BO12+Model!BP12+Model!BQ12+Model!BR12+Model!BS12),0) -> 0.10006683 | H17: =IF((Model!BT12+Model!BU12+Model!BV12+Model!BW12+Model!BX12+Model!BY12+Model!BZ12+Model!CA12+Model!CB12+Model!CC12+Model!CD12+Model!CE12)<>0,(Model!BT41+Model!BU41+Model!BV41+Model!BW41+Model!BX41+Model!BY41+Model!BZ41+Model!CA41+Model!CB41+Model!CC41+Model!CD41+Model!CE41)/(Model!BT12+Model!BU12+Model!BV12+Model!BW12+Model!BX12+Model!BY12+Model!BZ12+Model!CA12+Model!CB12+Model!CC12+Model!CD12+Model!CE12),0) -> 0.22241362 | I17: =IF((Model!CF12+Model!CG12+Model!CH12)<>0,(Model!CF41+Model!CG41+Model!CH41)/(Model!CF12+Model!CG12+Model!CH12),0) -> -0.092349347
A19: Six Peak Revenue | B19: =Model!C64+Model!D64+Model!E64+Model!F64+Model!G64+Model!H64+Model!I64+Model!J64+Model!K64 -> 370447.9 | C19: =Model!L64+Model!M64+Model!N64+Model!O64+Model!P64+Model!Q64+Model!R64+Model!S64+Model!T64+Model!U64+Model!V64+Model!W64 -> 314812.5 | D19: =Model!X64+Model!Y64+Model!Z64+Model!AA64+Model!AB64+Model!AC64+Model!AD64+Model!AE64+Model!AF64+Model!AG64+Model!AH64+Model!AI64 -> 200250 | E19: =Model!AJ64+Model!AK64+Model!AL64+Model!AM64+Model!AN64+Model!AO64+Model!AP64+Model!AQ64+Model!AR64+Model!AS64+Model!AT64+Model!AU64 -> 163365 | F19: =Model!AV64+Model!AW64+Model!AX64+Model!AY64+Model!AZ64+Model!BA64+Model!BB64+Model!BC64+Model!BD64+Model!BE64+Model!BF64+Model!BG64 -> 1276957 | G19: =Model!BH64+Model!BI64+Model!BJ64+Model!BK64+Model!BL64+Model!BM64+Model!BN64+Model!BO64+Model!BP64+Model!BQ64+Model!BR64+Model!BS64 -> 546560 | H19: =Model!BT64+Model!BU64+Model!BV64+Model!BW64+Model!BX64+Model!BY64+Model!BZ64+Model!CA64+Model!CB64+Model!CC64+Model!CD64+Model!CE64 -> 819993 | I19: =Model!CF64+Model!CG64+Model!CH64 -> 231016
A20: Six Peak Expenses | B20: =Model!C85+Model!D85+Model!E85+Model!F85+Model!G85+Model!H85+Model!I85+Model!J85+Model!K85 -> -1033925 | C20: =Model!L85+Model!M85+Model!N85+Model!O85+Model!P85+Model!Q85+Model!R85+Model!S85+Model!T85+Model!U85+Model!V85+Model!W85 -> -1368146 | D20: =Model!X85+Model!Y85+Model!Z85+Model!AA85+Model!AB85+Model!AC85+Model!AD85+Model!AE85+Model!AF85+Model!AG85+Model!AH85+Model!AI85 -> -1373598.9 | E20: =Model!AJ85+Model!AK85+Model!AL85+Model!AM85+Model!AN85+Model!AO85+Model!AP85+Model!AQ85+Model!AR85+Model!AS85+Model!AT85+Model!AU85 -> -1542525.9 | F20: =Model!AV85+Model!AW85+Model!AX85+Model!AY85+Model!AZ85+Model!BA85+Model!BB85+Model!BC85+Model!BD85+Model!BE85+Model!BF85+Model!BG85 -> -2661791.1 | G20: =Model!BH85+Model!BI85+Model!BJ85+Model!BK85+Model!BL85+Model!BM85+Model!BN85+Model!BO85+Model!BP85+Model!BQ85+Model!BR85+Model!BS85 -> -1817905.3 | H20: =Model!BT85+Model!BU85+Model!BV85+Model!BW85+Model!BX85+Model!BY85+Model!BZ85+Model!CA85+Model!CB85+Model!CC85+Model!CD85+Model!CE85 -> -1927994.2 | I20: =Model!CF85+Model!CG85+Model!CH85 -> -484961.69
A21: Six Peak Net Income | B21: =Model!C87+Model!D87+Model!E87+Model!F87+Model!G87+Model!H87+Model!I87+Model!J87+Model!K87 -> -663477.1 | C21: =Model!L87+Model!M87+Model!N87+Model!O87+Model!P87+Model!Q87+Model!R87+Model!S87+Model!T87+Model!U87+Model!V87+Model!W87 -> -1053333.5 | D21: =Model!X87+Model!Y87+Model!Z87+Model!AA87+Model!AB87+Model!AC87+Model!AD87+Model!AE87+Model!AF87+Model!AG87+Model!AH87+Model!AI87 -> -1173348.9 | E21: =Model!AJ87+Model!AK87+Model!AL87+Model!AM87+Model!AN87+Model!AO87+Model!AP87+Model!AQ87+Model!AR87+Model!AS87+Model!AT87+Model!AU87 -> -1379160.9 | F21: =Model!AV87+Model!AW87+Model!AX87+Model!AY87+Model!AZ87+Model!BA87+Model!BB87+Model!BC87+Model!BD87+Model!BE87+Model!BF87+Model!BG87 -> -1384834.1 | G21: =Model!BH87+Model!BI87+Model!BJ87+Model!BK87+Model!BL87+Model!BM87+Model!BN87+Model!BO87+Model!BP87+Model!BQ87+Model!BR87+Model!BS87 -> -1271345.3 | H21: =Model!BT87+Model!BU87+Model!BV87+Model!BW87+Model!BX87+Model!BY87+Model!BZ87+Model!CA87+Model!CB87+Model!CC87+Model!CD87+Model!CE87 -> -1108001.2 | I21: =Model!CF87+Model!CG87+Model!CH87 -> -253945.69
A23: Consolidated Net Income | B23: =Model!C96+Model!D96+Model!E96+Model!F96+Model!G96+Model!H96+Model!I96+Model!J96+Model!K96 -> 1781524.8 | C23: =Model!L96+Model!M96+Model!N96+Model!O96+Model!P96+Model!Q96+Model!R96+Model!S96+Model!T96+Model!U96+Model!V96+Model!W96 -> 2286419.4 | D23: =Model!X96+Model!Y96+Model!Z96+Model!AA96+Model!AB96+Model!AC96+Model!AD96+Model!AE96+Model!AF96+Model!AG96+Model!AH96+Model!AI96 -> 118287.05 | E23: =Model!AJ96+Model!AK96+Model!AL96+Model!AM96+Model!AN96+Model!AO96+Model!AP96+Model!AQ96+Model!AR96+Model!AS96+Model!AT96+Model!AU96 -> 616541.55 | F23: =Model!AV96+Model!AW96+Model!AX96+Model!AY96+Model!AZ96+Model!BA96+Model!BB96+Model!BC96+Model!BD96+Model!BE96+Model!BF96+Model!BG96 -> 892797.49 | G23: =Model!BH96+Model!BI96+Model!BJ96+Model!BK96+Model!BL96+Model!BM96+Model!BN96+Model!BO96+Model!BP96+Model!BQ96+Model!BR96+Model!BS96 -> -718811.34 | H23: =Model!BT96+Model!BU96+Model!BV96+Model!BW96+Model!BX96+Model!BY96+Model!BZ96+Model!CA96+Model!CB96+Model!CC96+Model!CD96+Model!CE96 -> 288309.56 | I23: =Model!CF96+Model!CG96+Model!CH96 -> -356026.55
A25: Steyn Group Fees
A26: Completion Guaranty Fee | B26: =Model!C80+Model!D80+Model!E80+Model!F80+Model!G80+Model!H80+Model!I80+Model!J80+Model!K80 -> 0 | C26: =Model!L80+Model!M80+Model!N80+Model!O80+Model!P80+Model!Q80+Model!R80+Model!S80+Model!T80+Model!U80+Model!V80+Model!W80 -> 0 | D26: =Model!X80+Model!Y80+Model!Z80+Model!AA80+Model!AB80+Model!AC80+Model!AD80+Model!AE80+Model!AF80+Model!AG80+Model!AH80+Model!AI80 -> 0 | E26: =Model!AJ80+Model!AK80+Model!AL80+Model!AM80+Model!AN80+Model!AO80+Model!AP80+Model!AQ80+Model!AR80+Model!AS80+Model!AT80+Model!AU80 -> 0 | F26: =Model!AV80+Model!AW80+Model!AX80+Model!AY80+Model!AZ80+Model!BA80+Model!BB80+Model!BC80+Model!BD80+Model!BE80+Model!BF80+Model!BG80 -> 0 | G26: =Model!BH80+Model!BI80+Model!BJ80+Model!BK80+Model!BL80+Model!BM80+Model!BN80+Model!BO80+Model!BP80+Model!BQ80+Model!BR80+Model!BS80 -> 0 | H26: =Model!BT80+Model!BU80+Model!BV80+Model!BW80+Model!BX80+Model!BY80+Model!BZ80+Model!CA80+Model!CB80+Model!CC80+Model!CD80+Model!CE80 -> 0 | I26: =Model!CF80+Model!CG80+Model!CH80 -> 0
A27: Liquidity Guarantee Fee | B27: =Model!C81+Model!D81+Model!E81+Model!F81+Model!G81+Model!H81+Model!I81+Model!J81+Model!K81 -> 0 | C27: =Model!L81+Model!M81+Model!N81+Model!O81+Model!P81+Model!Q81+Model!R81+Model!S81+Model!T81+Model!U81+Model!V81+Model!W81 -> 0 | D27: =Model!X81+Model!Y81+Model!Z81+Model!AA81+Model!AB81+Model!AC81+Model!AD81+Model!AE81+Model!AF81+Model!AG81+Model!AH81+Model!AI81 -> 0 | E27: =Model!AJ81+Model!AK81+Model!AL81+Model!AM81+Model!AN81+Model!AO81+Model!AP81+Model!AQ81+Model!AR81+Model!AS81+Model!AT81+Model!AU81 -> 0 | F27: =Model!AV81+Model!AW81+Model!AX81+Model!AY81+Model!AZ81+Model!BA81+Model!BB81+Model!BC81+Model!BD81+Model!BE81+Model!BF81+Model!BG81 -> 0 | G27: =Model!BH81+Model!BI81+Model!BJ81+Model!BK81+Model!BL81+Model!BM81+Model!BN81+Model!BO81+Model!BP81+Model!BQ81+Model!BR81+Model!BS81 -> 0 | H27: =Model!BT81+Model!BU81+Model!BV81+Model!BW81+Model!BX81+Model!BY81+Model!BZ81+Model!CA81+Model!CB81+Model!CC81+Model!CD81+Model!CE81 -> 0 | I27: =Model!CF81+Model!CG81+Model!CH81 -> 0
A28: Francis Steyn Fee + PIK (LIHTC) | B28: =Model!C82+Model!D82+Model!E82+Model!F82+Model!G82+Model!H82+Model!I82+Model!J82+Model!K82 -> 0 | C28: =Model!L82+Model!M82+Model!N82+Model!O82+Model!P82+Model!Q82+Model!R82+Model!S82+Model!T82+Model!U82+Model!V82+Model!W82 -> 0 | D28: =Model!X82+Model!Y82+Model!Z82+Model!AA82+Model!AB82+Model!AC82+Model!AD82+Model!AE82+Model!AF82+Model!AG82+Model!AH82+Model!AI82 -> 0 | E28: =Model!AJ82+Model!AK82+Model!AL82+Model!AM82+Model!AN82+Model!AO82+Model!AP82+Model!AQ82+Model!AR82+Model!AS82+Model!AT82+Model!AU82 -> -163365 | F28: =Model!AV82+Model!AW82+Model!AX82+Model!AY82+Model!AZ82+Model!BA82+Model!BB82+Model!BC82+Model!BD82+Model!BE82+Model!BF82+Model!BG82 -> -281718 | G28: =Model!BH82+Model!BI82+Model!BJ82+Model!BK82+Model!BL82+Model!BM82+Model!BN82+Model!BO82+Model!BP82+Model!BQ82+Model!BR82+Model!BS82 -> -134601.48 | H28: =Model!BT82+Model!BU82+Model!BV82+Model!BW82+Model!BX82+Model!BY82+Model!BZ82+Model!CA82+Model!CB82+Model!CC82+Model!CD82+Model!CE82 -> 0 | I28: =Model!CF82+Model!CG82+Model!CH82 -> 0
A29: Reseda Steyn Fee + PIK (LIHTC) | B29: =Model!C83+Model!D83+Model!E83+Model!F83+Model!G83+Model!H83+Model!I83+Model!J83+Model!K83 -> 0 | C29: =Model!L83+Model!M83+Model!N83+Model!O83+Model!P83+Model!Q83+Model!R83+Model!S83+Model!T83+Model!U83+Model!V83+Model!W83 -> 0 | D29: =Model!X83+Model!Y83+Model!Z83+Model!AA83+Model!AB83+Model!AC83+Model!AD83+Model!AE83+Model!AF83+Model!AG83+Model!AH83+Model!AI83 -> 0 | E29: =Model!AJ83+Model!AK83+Model!AL83+Model!AM83+Model!AN83+Model!AO83+Model!AP83+Model!AQ83+Model!AR83+Model!AS83+Model!AT83+Model!AU83 -> 0 | F29: =Model!AV83+Model!AW83+Model!AX83+Model!AY83+Model!AZ83+Model!BA83+Model!BB83+Model!BC83+Model!BD83+Model!BE83+Model!BF83+Model!BG83 -> -995239 | G29: =Model!BH83+Model!BI83+Model!BJ83+Model!BK83+Model!BL83+Model!BM83+Model!BN83+Model!BO83+Model!BP83+Model!BQ83+Model!BR83+Model!BS83 -> -292683 | H29: =Model!BT83+Model!BU83+Model!BV83+Model!BW83+Model!BX83+Model!BY83+Model!BZ83+Model!CA83+Model!CB83+Model!CC83+Model!CD83+Model!CE83 -> -312005 | I29: =Model!CF83+Model!CG83+Model!CH83 -> -74753.973
A30: 3rd St Steyn Fee + PIK (LIHTC) | B30: =Model!C84+Model!D84+Model!E84+Model!F84+Model!G84+Model!H84+Model!I84+Model!J84+Model!K84 -> 0 | C30: =Model!L84+Model!M84+Model!N84+Model!O84+Model!P84+Model!Q84+Model!R84+Model!S84+Model!T84+Model!U84+Model!V84+Model!W84 -> 0 | D30: =Model!X84+Model!Y84+Model!Z84+Model!AA84+Model!AB84+Model!AC84+Model!AD84+Model!AE84+Model!AF84+Model!AG84+Model!AH84+Model!AI84 -> 0 | E30: =Model!AJ84+Model!AK84+Model!AL84+Model!AM84+Model!AN84+Model!AO84+Model!AP84+Model!AQ84+Model!AR84+Model!AS84+Model!AT84+Model!AU84 -> 0 | F30: =Model!AV84+Model!AW84+Model!AX84+Model!AY84+Model!AZ84+Model!BA84+Model!BB84+Model!BC84+Model!BD84+Model!BE84+Model!BF84+Model!BG84 -> 0 | G30: =Model!BH84+Model!BI84+Model!BJ84+Model!BK84+Model!BL84+Model!BM84+Model!BN84+Model!BO84+Model!BP84+Model!BQ84+Model!BR84+Model!BS84 -> 0 | H30: =Model!BT84+Model!BU84+Model!BV84+Model!BW84+Model!BX84+Model!BY84+Model!BZ84+Model!CA84+Model!CB84+Model!CC84+Model!CD84+Model!CE84 -> -219466 | I30: =Model!CF84+Model!CG84+Model!CH84 -> -73155
A32: Debt Facilities
A33: Debt Facility Payment | B33: =Model!C101+Model!D101+Model!E101+Model!F101+Model!G101+Model!H101+Model!I101+Model!J101+Model!K101 -> -390000 | C33: =Model!L101+Model!M101+Model!N101+Model!O101+Model!P101+Model!Q101+Model!R101+Model!S101+Model!T101+Model!U101+Model!V101+Model!W101 -> -1495969.2 | D33: =Model!X101+Model!Y101+Model!Z101+Model!AA101+Model!AB101+Model!AC101+Model!AD101+Model!AE101+Model!AF101+Model!AG101+Model!AH101+Model!AI101 -> 0 | E33: =Model!AJ101+Model!AK101+Model!AL101+Model!AM101+Model!AN101+Model!AO101+Model!AP101+Model!AQ101+Model!AR101+Model!AS101+Model!AT101+Model!AU101 -> 0 | F33: =Model!AV101+Model!AW101+Model!AX101+Model!AY101+Model!AZ101+Model!BA101+Model!BB101+Model!BC101+Model!BD101+Model!BE101+Model!BF101+Model!BG101 -> 0 | G33: =Model!BH101+Model!BI101+Model!BJ101+Model!BK101+Model!BL101+Model!BM101+Model!BN101+Model!BO101+Model!BP101+Model!BQ101+Model!BR101+Model!BS101 -> 0 | H33: =Model!BT101+Model!BU101+Model!BV101+Model!BW101+Model!BX101+Model!BY101+Model!BZ101+Model!CA101+Model!CB101+Model!CC101+Model!CD101+Model!CE101 -> 0 | I33: =Model!CF101+Model!CG101+Model!CH101 -> 0
A34: Debt Facility Balance | B34: =Model!K102 -> 1404377.6 | C34: =Model!W102 -> 0 | D34: =Model!AI102 -> 0 | E34: =Model!AU102 -> 0 | F34: =Model!BG102 -> 0 | G34: =Model!BS102 -> 0 | H34: =Model!CE102 -> 0 | I34: =Model!CH102 -> 0
A35: Row Run Capital Payment | B35: =Model!C107+Model!D107+Model!E107+Model!F107+Model!G107+Model!H107+Model!I107+Model!J107+Model!K107 -> 0 | C35: =Model!L107+Model!M107+Model!N107+Model!O107+Model!P107+Model!Q107+Model!R107+Model!S107+Model!T107+Model!U107+Model!V107+Model!W107 -> -250000 | D35: =Model!X107+Model!Y107+Model!Z107+Model!AA107+Model!AB107+Model!AC107+Model!AD107+Model!AE107+Model!AF107+Model!AG107+Model!AH107+Model!AI107 -> -250000 | E35: =Model!AJ107+Model!AK107+Model!AL107+Model!AM107+Model!AN107+Model!AO107+Model!AP107+Model!AQ107+Model!AR107+Model!AS107+Model!AT107+Model!AU107 -> 0 | F35: =Model!AV107+Model!AW107+Model!AX107+Model!AY107+Model!AZ107+Model!BA107+Model!BB107+Model!BC107+Model!BD107+Model!BE107+Model!BF107+Model!BG107 -> 0 | G35: =Model!BH107+Model!BI107+Model!BJ107+Model!BK107+Model!BL107+Model!BM107+Model!BN107+Model!BO107+Model!BP107+Model!BQ107+Model!BR107+Model!BS107 -> 0 | H35: =Model!BT107+Model!BU107+Model!BV107+Model!BW107+Model!BX107+Model!BY107+Model!BZ107+Model!CA107+Model!CB107+Model!CC107+Model!CD107+Model!CE107 -> 0 | I35: =Model!CF107+Model!CG107+Model!CH107 -> 0
A36: Row Run Capital Balance | B36: =Model!K108 -> 1000000 | C36: =Model!W108 -> 750000 | D36: =Model!AI108 -> 500000 | E36: =Model!AU108 -> 500000 | F36: =Model!BG108 -> 500000 | G36: =Model!BS108 -> 500000 | H36: =Model!CE108 -> 500000 | I36: =Model!CH108 -> 500000
A37: PIK Repayment (in Steyn + PIK above) | B37: =Model!C155+Model!D155+Model!E155+Model!F155+Model!G155+Model!H155+Model!I155+Model!J155+Model!K155 -> 0 | C37: =Model!L155+Model!M155+Model!N155+Model!O155+Model!P155+Model!Q155+Model!R155+Model!S155+Model!T155+Model!U155+Model!V155+Model!W155 -> 0 | D37: =Model!X155+Model!Y155+Model!Z155+Model!AA155+Model!AB155+Model!AC155+Model!AD155+Model!AE155+Model!AF155+Model!AG155+Model!AH155+Model!AI155 -> 0 | E37: =Model!AJ155+Model!AK155+Model!AL155+Model!AM155+Model!AN155+Model!AO155+Model!AP155+Model!AQ155+Model!AR155+Model!AS155+Model!AT155+Model!AU155 -> 0 | F37: =Model!AV155+Model!AW155+Model!AX155+Model!AY155+Model!AZ155+Model!BA155+Model!BB155+Model!BC155+Model!BD155+Model!BE155+Model!BF155+Model!BG155 -> 0 | G37: =Model!BH155+Model!BI155+Model!BJ155+Model!BK155+Model!BL155+Model!BM155+Model!BN155+Model!BO155+Model!BP155+Model!BQ155+Model!BR155+Model!BS155 -> 0 | H37: =Model!BT155+Model!BU155+Model!BV155+Model!BW155+Model!BX155+Model!BY155+Model!BZ155+Model!CA155+Model!CB155+Model!CC155+Model!CD155+Model!CE155 -> 0 | I37: =Model!CF155+Model!CG155+Model!CH155 -> 0
A38: Investment Capital Outstanding | B38: =Model!K115+Model!K120+Model!K125+Model!K130 -> 2378399.9 | C38: =Model!W115+Model!W120+Model!W125+Model!W130 -> 1714451.1 | D38: =Model!AI115+Model!AI120+Model!AI125+Model!AI130 -> 1035128.5 | E38: =Model!AU115+Model!AU120+Model!AU125+Model!AU130 -> 1199352.1 | F38: =Model!BG115+Model!BG120+Model!BG125+Model!BG130 -> 975331.5 | G38: =Model!BS115+Model!BS120+Model!BS125+Model!BS130 -> 820735.29 | H38: =Model!CE115+Model!CE120+Model!CE125+Model!CE130 -> 621470.38 | I38: =Model!CH115+Model!CH120+Model!CH125+Model!CH130 -> 570021.55
A40: Bonding Outstanding | B40: =Model!K141 -> 90239874 | C40: =Model!W141 -> 56473336 | D40: =Model!AI141 -> 46152167 | E40: =Model!AU141 -> 13258585 | F40: =Model!BG141 -> 0 | G40: =Model!BS141 -> 0 | H40: =Model!CE141 -> 0 | I40: =Model!CH141 -> 0
A42: LV Ending Cash | B42: =Model!K148 -> 3470543.9 | C42: =Model!W148 -> 6810296.8 | D42: =Model!AI148 -> 8101932.8 | E42: =Model!AU148 -> 10097635 | F42: =Model!BG148 -> 12375267 | G42: =Model!BS148 -> 12927801 | H42: =Model!CE148 -> 14324112 | I42: =Model!CH148 -> 14222031
A43: SP Ending Cash | B43: =Model!K156 -> -815490.1 | C43: =Model!W156 -> -3614792.8 | D43: =Model!AI156 -> -5038141.8 | E43: =Model!AU156 -> -6417302.7 | F43: =Model!BG156 -> -7802136.8 | G43: =Model!BS156 -> -9073482.1 | H43: =Model!CE156 -> -10181483 | I43: =Model!CH156 -> -10435429
A44: Tax Distribution (30% Consol NI) | B44: =Model!C160+Model!D160+Model!E160+Model!F160+Model!G160+Model!H160+Model!I160+Model!J160+Model!K160 -> 0 | C44: =Model!L160+Model!M160+Model!N160+Model!O160+Model!P160+Model!Q160+Model!R160+Model!S160+Model!T160+Model!U160+Model!V160+Model!W160 -> -534457.45 | D44: =Model!X160+Model!Y160+Model!Z160+Model!AA160+Model!AB160+Model!AC160+Model!AD160+Model!AE160+Model!AF160+Model!AG160+Model!AH160+Model!AI160 -> -685925.82 | E44: =Model!AJ160+Model!AK160+Model!AL160+Model!AM160+Model!AN160+Model!AO160+Model!AP160+Model!AQ160+Model!AR160+Model!AS160+Model!AT160+Model!AU160 -> -35486.114 | F44: =Model!AV160+Model!AW160+Model!AX160+Model!AY160+Model!AZ160+Model!BA160+Model!BB160+Model!BC160+Model!BD160+Model!BE160+Model!BF160+Model!BG160 -> -184962.46 | G44: =Model!BH160+Model!BI160+Model!BJ160+Model!BK160+Model!BL160+Model!BM160+Model!BN160+Model!BO160+Model!BP160+Model!BQ160+Model!BR160+Model!BS160 -> -267839.25 | H44: =Model!BT160+Model!BU160+Model!BV160+Model!BW160+Model!BX160+Model!BY160+Model!BZ160+Model!CA160+Model!CB160+Model!CC160+Model!CD160+Model!CE160 -> 0 | I44: =Model!CF160+Model!CG160+Model!CH160 -> -86492.867
A45: Total Ending Cash | B45: =Model!K161 -> 2655053.8 | C45: =Model!W161 -> 3195504 | D45: =Model!AI161 -> 3063791 | E45: =Model!AU161 -> 3680332.6 | F45: =Model!BG161 -> 4573130.1 | G45: =Model!BS161 -> 3854318.7 | H45: =Model!CE161 -> 4142628.3 | I45: =Model!CH161 -> 3700108.9

Sheet Model
A1: Six Peak Capital - Financial Projections
C2: 46113 | D2: 46143 | E2: 46174 | F2: 46204 | G2: 46235 | H2: 46266 | I2: 46296 | J2: 46327 | K2: 46357 | L2: 46388 | M2: 46419 | N2: 46447 | O2: 46478 | P2: 46508 | Q2: 46539 | R2: 46569 | S2: 46600 | T2: 46631 | U2: 46661 | V2: 46692 | W2: 46722 | X2: 46753 | Y2: 46784 | Z2: 46813 | AA2: 46844 | AB2: 46874 | AC2: 46905 | AD2: 46935 | AE2: 46966 | AF2: 46997 | AG2: 47027 | AH2: 47058 | AI2: 47088 | AJ2: 47119 | AK2: 47150 | AL2: 47178 | AM2: 47209 | AN2: 47239 | AO2: 47270 | AP2: 47300 | AQ2: 47331 | AR2: 47362 | AS2: 47392 | AT2: 47423 | AU2: 47453 | AV2: 47484 | AW2: 47515 | AX2: 47543 | AY2: 47574 | AZ2: 47604 | BA2: 47635 | BB2: 47665 | BC2: 47696 | BD2: 47727 | BE2: 47757 | BF2: 47788 | BG2: 47818 | BH2: 47849 | BI2: 47880 | BJ2: 47908 | BK2: 47939 | BL2: 47969 | BM2: 48000 | BN2: 48030 | BO2: 48061 | BP2: 48092 | BQ2: 48122 | BR2: 48153 | BS2: 48183 | BT2: 48214 | BU2: 48245 | BV2: 48274 | BW2: 48305 | BX2: 48335 | BY2: 48366 | BZ2: 48396 | CA2: 48427 | CB2: 48458 | CC2: 48488 | CD2: 48519 | CE2: 48549 | CF2: 48580 | CG2: 48611 | CH2: 48639
A3: Month # | C3: 1 | D3: 2 | E3: 3 | F3: 4 | G3: 5 | H3: 6 | I3: 7 | J3: 8 | K3: 9 | L3: 10 | M3: 11 | N3: 12 | O3: 13 | P3: 14 | Q3: 15 | R3: 16 | S3: 17 | T3: 18 | U3: 19 | V3: 20 | W3: 21 | X3: 22 | Y3: 23 | Z3: 24 | AA3: 25 | AB3: 26 | AC3: 27 | AD3: 28 | AE3: 29 | AF3: 30 | AG3: 31 | AH3: 32 | AI3: 33 | AJ3: 34 | AK3: 35 | AL3: 36 | AM3: 37 | AN3: 38 | AO3: 39 | AP3: 40 | AQ3: 41 | AR3: 42 | AS3: 43 | AT3: 44 | AU3: 45 | AV3: 46 | AW3: 47 | AX3: 48 | AY3: 49 | AZ3: 50 | BA3: 51 | BB3: 52 | BC3: 53 | BD3: 54 | BE3: 55 | BF3: 56 | BG3: 57 | BH3: 58 | BI3: 59 | BJ3: 60 | BK3: 61 | BL3: 62 | BM3: 63 | BN3: 64 | BO3: 65 | BP3: 66 | BQ3: 67 | BR3: 68 | BS3: 69 | BT3: 70 | BU3: 71 | BV3: 72 | BW3: 73 | BX3: 74 | BY3: 75 | BZ3: 76 | CA3: 77 | CB3: 78 | CC3: 79 | CD3: 80 | CE3: 81 | CF3: 82 | CG3: 83 | CH3: 84
A5: GC CONSTRUCTION P&L | C5: Crenshaw, Ramsgate, Califa, Whipple, Nelrose | F5: Francis | G5: Klump | H5: Scott | I5: Lexington, Denny | J5: Acama | O5: Reseda | R5: HVN Pipeline 1 | U5: HVN Pipeline 2 | AC5: 3rd St
A6: GC Revenue
